{
  "$schema": "https://raw.githubusercontent.com/spdx/spdx-spec/v2.2.1/schemas/spdx-schema.json",
  "spdxVersion": "SPDX-2.2",
  "dataLicense": "CC0-1.0",
  "SPDXID": "SPDXRef-DOCUMENT",
  "documentNamespace": "https://spdx.org/spdxdocs/boost-multiprecision-x64-linux-1.82.0#1-ed4cc4d3-7239-41d5-97ef-050921d106a0",
  "name": "boost-multiprecision:x64-linux@1.82.0#1 6805a59891cbfbeed37ef987418cc14e4a9263b31c4c869fbba267d05bf6f69e",
  "creationInfo": {
    "creators": [
      "Tool: vcpkg-664f8bb619b752430368d0f30a8289b761f5caba"
    ],
    "created": "2023-04-23T23:40:38Z"
  },
  "relationships": [
    {
      "spdxElementId": "SPDXRef-port",
      "relationshipType": "GENERATES",
      "relatedSpdxElement": "SPDXRef-binary"
    },
    {
      "spdxElementId": "SPDXRef-port",
      "relationshipType": "CONTAINS",
      "relatedSpdxElement": "SPDXRef-file-0"
    },
    {
      "spdxElementId": "SPDXRef-port",
      "relationshipType": "CONTAINS",
      "relatedSpdxElement": "SPDXRef-file-1"
    },
    {
      "spdxElementId": "SPDXRef-binary",
      "relationshipType": "GENERATED_FROM",
      "relatedSpdxElement": "SPDXRef-port"
    },
    {
      "spdxElementId": "SPDXRef-file-0",
      "relationshipType": "CONTAINED_BY",
      "relatedSpdxElement": "SPDXRef-port"
    },
    {
      "spdxElementId": "SPDXRef-file-1",
      "relationshipType": "CONTAINED_BY",
      "relatedSpdxElement": "SPDXRef-port"
    },
    {
      "spdxElementId": "SPDXRef-file-1",
      "relationshipType": "DEPENDENCY_MANIFEST_OF",
      "relatedSpdxElement": "SPDXRef-port"
    }
  ],
  "packages": [
    {
      "name": "boost-multiprecision",
      "SPDXID": "SPDXRef-port",
      "versionInfo": "1.82.0#1",
      "downloadLocation": "NOASSERTION",
      "homepage": "https://github.com/boostorg/multiprecision",
      "licenseConcluded": "BSL-1.0",
      "licenseDeclared": "NOASSERTION",
      "copyrightText": "NOASSERTION",
      "description": "Boost multiprecision module",
      "comment": "This is the port (recipe) consumed by vcpkg."
    },
    {
      "name": "boost-multiprecision:x64-linux",
      "SPDXID": "SPDXRef-binary",
      "versionInfo": "6805a59891cbfbeed37ef987418cc14e4a9263b31c4c869fbba267d05bf6f69e",
      "downloadLocation": "NONE",
      "licenseConcluded": "BSL-1.0",
      "licenseDeclared": "NOASSERTION",
      "copyrightText": "NOASSERTION",
      "comment": "This is a binary package built by vcpkg."
    },
    {
      "SPDXID": "SPDXRef-resource-1",
      "name": "boostorg/multiprecision",
      "downloadLocation": "git+https://github.com/boostorg/multiprecision@boost-1.82.0",
      "licenseConcluded": "NOASSERTION",
      "licenseDeclared": "NOASSERTION",
      "copyrightText": "NOASSERTION",
      "checksums": [
        {
          "algorithm": "SHA512",
          "checksumValue": "f2441a918e595dca1c2618ff37a5ddebb3bc9e6b923e27e2604ea7ec8f003621b2506f4fd1ec41b3ed3de68c01cd19ff637e205aad0341d272a63edf1469ba5c"
        }
      ]
    }
  ],
  "files": [
    {
      "fileName": "./portfile.cmake",
      "SPDXID": "SPDXRef-file-0",
      "checksums": [
        {
          "algorithm": "SHA256",
          "checksumValue": "8449a363051dcbae377cf72f94f51cbf7588b243805f6ef1668e8496490d61bb"
        }
      ],
      "licenseConcluded": "NOASSERTION",
      "copyrightText": "NOASSERTION"
    },
    {
      "fileName": "./vcpkg.json",
      "SPDXID": "SPDXRef-file-1",
      "checksums": [
        {
          "algorithm": "SHA256",
          "checksumValue": "20fb59fb44c9af7129f816de7b0a8bc2268c11ec313e7ddefe7c1f80b095f289"
        }
      ],
      "licenseConcluded": "NOASSERTION",
      "copyrightText": "NOASSERTION"
    }
  ]
}
